Metadata-Version: 2.4
Name: mseep-suzieq-mcp
Version: 0.1.4
Summary: Add your description here
Author-email: mseep <support@skydeck.ai>
Requires-Python: >=3.12
License-File: LICENSE
Requires-Dist: httpx>=0.28.1
Requires-Dist: python-dotenv>=1.0.0
Requires-Dist: mcp[cli]>=1.6.0
Dynamic: license-file
